librclone/__init__.py
librclone/lib/librclone.h
librclone/lib/librclone.so
librclone/rclone.py
librclone/test_rclone.py
librclone-1.62.2.dist-info/METADATA
librclone-1.62.2.dist-info/WHEEL
librclone-1.62.2.dist-info/RECORD
