Metadata-Version: 2.3
Name: librclone
Version: 1.62.2
Summary: Small wrapper around `librclone` to allow RPC calls to RClone from Python
Author: Nick Craig-Wood
Author-email: nick@craig-wood.com
Maintainer: Pratheek Rebala
Maintainer-email: pratheekrebala@gmail.com
Classifier: Programming Language :: Python :: 2
Classifier: Programming Language :: Python :: 2.7
Classifier: Programming Language :: Python :: 3
Classifier: Programming Language :: Python :: 3.4
Classifier: Programming Language :: Python :: 3.5
Classifier: Programming Language :: Python :: 3.6
Classifier: Programming Language :: Python :: 3.7
Classifier: Programming Language :: Python :: 3.8
Classifier: Programming Language :: Python :: 3.9
Classifier: Programming Language :: Python :: 3.10
Classifier: Programming Language :: Python :: 3.11
Classifier: Programming Language :: Python :: 3.12
Classifier: Programming Language :: Python :: 3.13
